robinhood_scraper_nlp/__init__.py
robinhood_scraper_nlp/cleaner.py
robinhood_scraper_nlp/news_article_data.py
robinhood_scraper_nlp/parser.py
robinhood_scraper_nlp/runner.py
robinhood_scraper_nlp/scorer.py
robinhood_scraper_nlp/script.py
robinhood_scraper_nlp/model/__init__.py
robinhood_scraper_nlp/model/article_data.py
robinhood_scraper_nlp/models/__init__.py
robinhood_scraper_nlp/models/article_data.py
robinhood_scraper_nlp/utils/__init__.py
robinhood_scraper_nlp/utils/cleaner.py
robinhood_scraper_nlp/utils/scorer.py
robinhood_scraper_nlp-0.0.6.dist-info/LICENSE
robinhood_scraper_nlp-0.0.6.dist-info/METADATA
robinhood_scraper_nlp-0.0.6.dist-info/WHEEL
robinhood_scraper_nlp-0.0.6.dist-info/top_level.txt
robinhood_scraper_nlp-0.0.6.dist-info/RECORD
