Metadata-Version: 2.1
Name: robinhood-scraper-nlp
Version: 0.0.6
Summary: A package that interacts with Robinhood APIs to access news about stocks
Home-page: https://github.com/EcZachly/robinhood-nlp
Author: Zachary Wilson
Author-email: zachwilson130@gmail.com
License: UNKNOWN
Platform: UNKNOWN
Classifier: Programming Language :: Python :: 3
Classifier: License :: OSI Approved :: MIT License
Classifier: Operating System :: OS Independent
Requires-Python: >=3.6
